README.rst
setup.py
globtailer/__init__.py
globtailer/main.py
globtailer/tests.py
globtailer.egg-info/PKG-INFO
globtailer.egg-info/SOURCES.txt
globtailer.egg-info/dependency_links.txt
globtailer.egg-info/entry_points.txt
globtailer.egg-info/not-zip-safe
globtailer.egg-info/top_level.txt